src/__init__.py
src/student_records.py
mypackage_student_records-0.12.dist-info/METADATA
mypackage_student_records-0.12.dist-info/WHEEL
mypackage_student_records-0.12.dist-info/top_level.txt
mypackage_student_records-0.12.dist-info/RECORD
