Metadata-Version: 2.1
Name: mypackage-student-records
Version: 0.12
Summary: Progetto di Produzione del Software
Home-page: https://gitlab.com/MarcecaManu/2023_assignment1_student_records
Author: SMJ
Author-email: s.madaghiele@campus.unimib.it
Requires-Dist: requirements.txt
